{
    "selected": true,
    "type": [
        "null",
        "object"
    ],
    "additionalProperties": false,
    "properties": {
        "app": {
            "type": "string"
        },
        "app_id": {
            "type": "string"
        },
        "charge_id": {
            "type": [
				"null",
				"string"
			]
        },
        "created_at": {
            "type": "string",
            "format": "date-time"
        },
        "gross_amount": {
            "type": "number"
        },
        "gross_amount_currency_code": {
            "type": "string"
        },
        "id": {
            "type": "string"
        },
        "net_amount": {
            "type": "number"
        },
        "net_amount_currency_code": {
            "type": "string"
        },
        "shop_domain": {
            "type": "string"
        },
        "shop_name": {
            "type": "string"
        },
        "shop_id": {
            "type": "string"
        },
        "shopify_fee": {
            "type": "number"
        },
        "shopify_fee_currency_code": {
            "type": "string"
        }
    }
}